bookmarkarchiver.py
bookmark_archiver-1.0.0.dist-info/LICENSE
bookmark_archiver-1.0.0.dist-info/METADATA
bookmark_archiver-1.0.0.dist-info/WHEEL
bookmark_archiver-1.0.0.dist-info/top_level.txt
bookmark_archiver-1.0.0.dist-info/RECORD
