Metadata-Version: 2.1
Name: bookmark-archiver
Version: 1.0.0
Summary: Archive your Chrome and Firefox bookmarks
Author-email: Anthony Chen <chenanthony365@gmail.com>
Project-URL: Homepage, https://github.com/slightlyskepticalpotat/bookmark-archiver
Project-URL: Bug Tracker, https://github.com/slightlyskepticalpotat/bookmark-archiver/issues
Classifier: Programming Language :: Python :: 3
Classifier: License :: OSI Approved :: GNU General Public License v3 (GPLv3)
Classifier: Operating System :: OS Independent
Requires-Python: >=3.6
License-File: LICENSE
